{
  "superheroes": [
    {
      "id": 1,
      "name": "Batman",
      "alterEgo": "Bruce Wayne"
    },
    {
      "id": 2,
      "name": "Superman",
      "alterEgo": "Clark kent"
    },
    {
      "id": 3,
      "name": "Wonder Woman",
      "alterEgo": "Princess Diana"
    },
    {
      "id": 4,
      "name": "Spiderman",
      "alterEgo": "Peter Parker"
    }
  ],
  "friends": [
    { "id": 1, "name": "Joey Tribbiani" },
    { "id": 2, "name": "Phoebe Buffay" },
    { "id": 3, "name": "Rechael Green" },
    { "id": 4, "name": "Chandler Bing" }
  ]
}
